pysecstring/__init__.py
pysecstring/main.py
pysecstring-0.1.9.dist-info/WHEEL
pysecstring-0.1.9.dist-info/METADATA
pysecstring-0.1.9.dist-info/RECORD
